LICENSE
MANIFEST.in
README.md
setup.cfg
setup.py
py3webfuzz/__init__.py
py3webfuzz/__main__.py
py3webfuzz/encoderFuncs.py
py3webfuzz/fuzzdb.py
py3webfuzz/utils.py
py3webfuzz.egg-info/PKG-INFO
py3webfuzz.egg-info/SOURCES.txt
py3webfuzz.egg-info/dependency_links.txt
py3webfuzz.egg-info/requires.txt
py3webfuzz.egg-info/top_level.txt
py3webfuzz/test_examples/CodecsTest.py
py3webfuzz/test_examples/test_sqli-1.py
py3webfuzz/test_examples/utils-test.py