Metadata-Version: 2.1
Name: py3webfuzz
Version: 0.1.7
Summary: A Python3 module to assist in fuzzing web applications
Home-page: https://github.com/jangelesg/py3webfuzz
Author: Jonathan Angeles
Author-email: jangelesg@gangsecurity.com
License: GPLv3
Download-URL: https://github.com/jangelesg/py3webfuzz/archive/0.1.7.tar.gz
Keywords: fuzz pentest security
Platform: Linux
Platform: Windows
Platform: macOs
Classifier: Environment :: Web Environment
Classifier: Intended Audience :: Information Technology
Classifier: License :: OSI Approved :: GNU General Public License v2 (GPLv2)
Classifier: Operating System :: OS Independent
Classifier: Programming Language :: Python :: 3.8
Classifier: Topic :: Internet
Classifier: Topic :: Security
